__init__.py
stationarity_toolkit/__init__.py
stationarity_toolkit/stationarity_toolkit.py
stationaritytoolkit-0.1.5.dist-info/licenses/LICENSE
stationaritytoolkit-0.1.5.dist-info/METADATA
stationaritytoolkit-0.1.5.dist-info/WHEEL
stationaritytoolkit-0.1.5.dist-info/top_level.txt
stationaritytoolkit-0.1.5.dist-info/RECORD
