Metadata-Version: 2.4
Name: stationaritytoolkit
Version: 0.1.5
Summary: Test and Convert non-stationary time-series to stationary
Author-email: Bhanu Suraj Malla <bsmalla@asu.edu>
Project-URL: Homepage, https://github.com/mbsuraj/stationarityToolkit
Project-URL: Bug Tracker, https://github.com/mbsuraj/stationarityToolkit/issues
Classifier: Programming Language :: Python :: 3
Classifier: License :: Other/Proprietary License
Classifier: Operating System :: OS Independent
Requires-Python: >=3.7
License-File: LICENSE
Dynamic: license-file
